{
  "schema_version": "visual-signature-category-seed-1",
  "corpus_version": "0.1.0",
  "category": "nonprofit_education",
  "display_name": "Nonprofit/education",
  "records": [
    {"schema_version":"visual-signature-corpus-record-1","corpus_version":"0.1.0","brand_name":"Khan Academy","website_url":"https://www.khanacademy.org","category":"nonprofit_education","subcategory":"education_platform","selection_reason":"Education nonprofit with broad audience and practical product flows.","brand_fame_level":"high","design_maturity_label":"medium","baseline_eligible":false},
    {"schema_version":"visual-signature-corpus-record-1","corpus_version":"0.1.0","brand_name":"Charity Water","website_url":"https://www.charitywater.org","category":"nonprofit_education","subcategory":"water_access_nonprofit","selection_reason":"Nonprofit with campaign storytelling and donation conversion.","brand_fame_level":"medium","design_maturity_label":"high","baseline_eligible":false},
    {"schema_version":"visual-signature-corpus-record-1","corpus_version":"0.1.0","brand_name":"Coursera","website_url":"https://www.coursera.org","category":"nonprofit_education","subcategory":"commercial_education_platform","selection_reason":"Education platform with marketplace and credential messaging.","brand_fame_level":"high","design_maturity_label":"medium","baseline_eligible":false},
    {"schema_version":"visual-signature-corpus-record-1","corpus_version":"0.1.0","brand_name":"edX","website_url":"https://www.edx.org","category":"nonprofit_education","subcategory":"institutional_course_marketplace","selection_reason":"Education platform with institutional trust and course discovery.","brand_fame_level":"high","design_maturity_label":"medium","baseline_eligible":false},
    {"schema_version":"visual-signature-corpus-record-1","corpus_version":"0.1.0","brand_name":"Codecademy","website_url":"https://www.codecademy.com","category":"nonprofit_education","subcategory":"commercial_coding_learning_platform","selection_reason":"Learning platform with product-led education conversion patterns.","brand_fame_level":"high","design_maturity_label":"medium","baseline_eligible":false},
    {"schema_version":"visual-signature-corpus-record-1","corpus_version":"0.1.0","brand_name":"freeCodeCamp","website_url":"https://www.freecodecamp.org","category":"nonprofit_education","subcategory":"developer_education","selection_reason":"Nonprofit education site with utilitarian and community-first behavior.","brand_fame_level":"high","design_maturity_label":"low","baseline_eligible":false},
    {"schema_version":"visual-signature-corpus-record-1","corpus_version":"0.1.0","brand_name":"DonorsChoose","website_url":"https://www.donorschoose.org","category":"nonprofit_education","subcategory":"education_nonprofit","selection_reason":"Donation marketplace with practical trust and cause-driven UI.","brand_fame_level":"medium","design_maturity_label":"medium","baseline_eligible":false},
    {"schema_version":"visual-signature-corpus-record-1","corpus_version":"0.1.0","brand_name":"Girls Who Code","website_url":"https://girlswhocode.com","category":"nonprofit_education","subcategory":"education_nonprofit","selection_reason":"Mission-led education nonprofit with editorial and donation flows.","brand_fame_level":"medium","design_maturity_label":"medium","baseline_eligible":false},
    {"schema_version":"visual-signature-corpus-record-1","corpus_version":"0.1.0","brand_name":"Code.org","website_url":"https://code.org","category":"nonprofit_education","subcategory":"education_nonprofit","selection_reason":"Large education nonprofit with practical student/teacher navigation.","brand_fame_level":"high","design_maturity_label":"medium","baseline_eligible":false},
    {"schema_version":"visual-signature-corpus-record-1","corpus_version":"0.1.0","brand_name":"One Tree Planted","website_url":"https://onetreeplanted.org","category":"nonprofit_education","subcategory":"environment_nonprofit","selection_reason":"Nonprofit with ecommerce-like donation and campaign visuals.","brand_fame_level":"medium","design_maturity_label":"medium","baseline_eligible":false},
    {"schema_version":"visual-signature-corpus-record-1","corpus_version":"0.1.0","brand_name":"826 National","website_url":"https://826national.org","category":"nonprofit_education","subcategory":"education_nonprofit","selection_reason":"Lower-fame education nonprofit with modest but distinctive visual system.","brand_fame_level":"low","design_maturity_label":"medium","baseline_eligible":false},
    {"schema_version":"visual-signature-corpus-record-1","corpus_version":"0.1.0","brand_name":"826 Valencia","website_url":"https://826valencia.org","category":"nonprofit_education","subcategory":"education_nonprofit","selection_reason":"Local education nonprofit candidate to reduce famous-institution overfitting.","brand_fame_level":"low","design_maturity_label":"low","baseline_eligible":false}
  ]
}
